LICENSE
MANIFEST.in
README.md
setup.py
bin/show
showtools/__init__.py
showtools/__main__.py
showtools.egg-info/PKG-INFO
showtools.egg-info/SOURCES.txt
showtools.egg-info/dependency_links.txt
showtools.egg-info/entry_points.txt
showtools.egg-info/requires.txt
showtools.egg-info/top_level.txt
showtools/showlib/__init__.py
showtools/showlib/argparsing.py
showtools/showlib/disk.py
showtools/showlib/diskattr.py
showtools/showlib/disklookup.py
showtools/showlib/displaytable.py
showtools/showlib/netattr.py
showtools/showlib/netlookup.py
showtools/showlib/network.py
showtools/showlib/processdevice.py
showtools/showlib/smart.py