Metadata-Version: 2.1
Name: showtools
Version: 2.0.2
Summary: Show storage and network devices in table format on cli
Home-page: https://github.com/louwrentius/showtools/
Author: louwrentius
License-File: LICENSE
Requires-Dist: rich
